nbu_exchange_rates/__init__.py
nbu_exchange_rates/exchange_rates.py
nbu_exchange_rates-1.0.1.dist-info/LICENSE
nbu_exchange_rates-1.0.1.dist-info/METADATA
nbu_exchange_rates-1.0.1.dist-info/WHEEL
nbu_exchange_rates-1.0.1.dist-info/top_level.txt
nbu_exchange_rates-1.0.1.dist-info/RECORD
