Metadata-Version: 2.1
Name: nbu-exchange-rates
Version: 1.0.1
Summary: A small library for getting information on cash exchange rates of the NBU for the selected date range
Home-page: UNKNOWN
Author: Oleksandr Sokyrka
Author-email: sokyrkals@gmail.com
License: MIT
Project-URL: Source, https://github.com/lesykbiceps/nbu-exchange-rates
Keywords: python,exchange rate,nbu,bank,Ukrainian,diagram,chart,graph
Platform: UNKNOWN
Classifier: Intended Audience :: Education
Classifier: Programming Language :: Python :: 3
Classifier: License :: OSI Approved :: MIT License
Classifier: Operating System :: OS Independent
Requires-Dist: matplotlib
Requires-Dist: requests
